<?xml version="1.0"?>
<!DOCTYPE hibernate-mapping PUBLIC "-//Hibernate/Hibernate Mapping DTD 3.0//EN"
"http://hibernate.sourceforge.net/hibernate-mapping-3.0.dtd">
<!-- 
    Mapping file autogenerated by MyEclipse - Hibernate Tools
-->
<hibernate-mapping>
    <class name="com.stuman.domain.Student" table="student" lazy="false">
        <id name="id" type="string">
            <column name="id" length="32" />
            <generator class="assigned" />
        </id>
        <property name="name" type="string">
            <column name="name" length="32" />
        </property>
        <property name="password" type="string">
            <column name="password" length="32" />
        </property>
        <property name="jiguan" type="string">
            <column name="jiguan" length="32" />
        </property>
        <property name="department" type="string">
            <column name="department" length="32" />
        </property>
        <property name="sex" type="string">
            <column name="sex" length="32" />
        </property>
        <property name="mark" type="integer">
            <column name="mark" />
        </property>
        <property name="tel" type="string">
            <column name="tel" length="32" />
        </property>
        <property name="phone" type="string">
            <column name="phone" length="32" />
        </property>
        <property name="email" type="string">
            <column name="email" length="32" />
        </property>
        <set name="enrols" inverse="true">
            <key>
                <column name="stu_id" length="32" />
            </key>
            <one-to-many class="com.stuman.domain.Enrol" />
        </set>
    </class>
</hibernate-mapping>
